<country>
  <name>Timor-Leste</name>
  <area>
    <vertex lat="-9.41374033" lon="124.31931644"/>
    <vertex lat="-9.42789967" lon="124.28231612"/>
    <vertex lat="-9.41384368" lon="124.1345732"/>
    <vertex lat="-9.42314544" lon="124.11555627"/>
    <vertex lat="-9.4164275" lon="124.09013146"/>
    <vertex lat="-9.37539642" lon="124.05240767"/>
    <vertex lat="-9.34160003" lon="124.03638797"/>
    <vertex lat="-9.25612721" lon="124.19813521"/>
    <vertex lat="-9.19034311" lon="124.44442508"/>
    <vertex lat="-9.23855722" lon="124.43822391"/>
    <vertex lat="-9.31431487" lon="124.41300581"/>
    <vertex lat="-9.34991994" lon="124.37569543"/>
    <vertex lat="-9.41374033" lon="124.31931644"/>
  </area>
  <area>
    <vertex lat="-8.42455006" lon="127.29613732"/>
    <vertex lat="-8.58355844" lon="127.11454634"/>
    <vertex lat="-8.71528167" lon="126.91517866"/>
    <vertex lat="-8.7551242" lon="126.79249881"/>
    <vertex lat="-8.78199594" lon="126.66547814"/>
    <vertex lat="-8.83289723" lon="126.56853316"/>
    <vertex lat="-8.91268564" lon="126.48688439"/>
    <vertex lat="-8.95759246" lon="126.382498"/>
    <vertex lat="-8.97273366" lon="126.26477909"/>
    <vertex lat="-8.99671152" lon="126.16421675"/>
    <vertex lat="-9.04358205" lon="126.07305952"/>
    <vertex lat="-9.1239389" lon="125.94614221"/>
    <vertex lat="-9.13210377" lon="125.89477583"/>
    <vertex lat="-9.13014007" lon="125.84030887"/>
    <vertex lat="-9.16093922" lon="125.73519901"/>
    <vertex lat="-9.27576426" lon="125.40798384"/>
    <vertex lat="-9.40356007" lon="125.21026981"/>
    <vertex lat="-9.51192555" lon="125.06810794"/>
    <vertex lat="-9.38185597" lon="125.03363976"/>
    <vertex lat="-9.32599375" lon="124.9969495"/>
    <vertex lat="-9.29426442" lon="124.96826908"/>
    <vertex lat="-9.25468027" lon="124.95860558"/>
    <vertex lat="-9.21380421" lon="124.96015588"/>
    <vertex lat="-9.19494232" lon="124.97751916"/>
    <vertex lat="-9.18982635" lon="125.10050907"/>
    <vertex lat="-9.12290537" lon="125.14944665"/>
    <vertex lat="-9.04254852" lon="125.14898156"/>
    <vertex lat="-9.01541839" lon="125.12443526"/>
    <vertex lat="-9.0039979" lon="125.10035404"/>
    <vertex lat="-9.06430429" lon="124.97328169"/>
    <vertex lat="-9.05345224" lon="124.93684981"/>
    <vertex lat="-9.03154144" lon="124.91509403"/>
    <vertex lat="-8.94250294" lon="124.92227705"/>
    <vertex lat="-8.85904551" lon="125.02692183"/>
    <vertex lat="-8.70804697" lon="125.11570194"/>
    <vertex lat="-8.64784393" lon="125.17802372"/>
    <vertex lat="-8.59130991" lon="125.32313114"/>
    <vertex lat="-8.57534189" lon="125.38183557"/>
    <vertex lat="-8.49214284" lon="125.80423872"/>
    <vertex lat="-8.48656178" lon="125.90511112"/>
    <vertex lat="-8.4889389" lon="126.17279504"/>
    <vertex lat="-8.47080047" lon="126.53101607"/>
    <vertex lat="-8.45948333" lon="126.61969282"/>
    <vertex lat="-8.42279306" lon="126.73451786"/>
    <vertex lat="-8.3773178" lon="126.84572554"/>
    <vertex lat="-8.34155771" lon="126.90463667"/>
    <vertex lat="-8.3157195" lon="126.96644169"/>
    <vertex lat="-8.34827565" lon="127.05852909"/>
    <vertex lat="-8.37297698" lon="127.21479862"/>
    <vertex lat="-8.39457773" lon="127.25706994"/>
    <vertex lat="-8.42455006" lon="127.29613732"/>
  </area>
  <area>
    <vertex lat="-8.13991627" lon="125.64610884"/>
    <vertex lat="-8.31179209" lon="125.57944624"/>
    <vertex lat="-8.27510182" lon="125.50709924"/>
    <vertex lat="-8.17857024" lon="125.58409712"/>
    <vertex lat="-8.15004485" lon="125.62109745"/>
    <vertex lat="-8.13991627" lon="125.64610884"/>
  </area>
</country>
