<country>
  <name>Djibouti</name>
  <area>
    <vertex lat="11.49981517" lon="43.24597049"/>
    <vertex lat="11.36571483" lon="43.15941247"/>
    <vertex lat="11.19432994" lon="43.04866987"/>
    <vertex lat="10.99930309" lon="42.92273441"/>
    <vertex lat="10.9979595" lon="42.84413456"/>
    <vertex lat="11.00927664" lon="42.78294966"/>
    <vertex lat="11.04237539" lon="42.74124678"/>
    <vertex lat="11.07834219" lon="42.65499881"/>
    <vertex lat="11.08077098" lon="42.55774377"/>
    <vertex lat="11.04707795" lon="42.4651396"/>
    <vertex lat="11.00522004" lon="42.30809492"/>
    <vertex lat="10.99157746" lon="42.16624312"/>
    <vertex lat="10.9683489" lon="42.05214155"/>
    <vertex lat="10.94103791" lon="41.95747033"/>
    <vertex lat="10.95581737" lon="41.87220422"/>
    <vertex lat="10.98046703" lon="41.79820357"/>
    <vertex lat="11.18779287" lon="41.78208052"/>
    <vertex lat="11.41289541" lon="41.76466556"/>
    <vertex lat="11.58911205" lon="41.76652591"/>
    <vertex lat="11.68605703" lon="41.79267419"/>
    <vertex lat="11.72378083" lon="41.8156702"/>
    <vertex lat="11.85788117" lon="41.94961551"/>
    <vertex lat="11.91237397" lon="41.99586592"/>
    <vertex lat="12.13414338" lon="42.14908654"/>
    <vertex lat="12.32426097" lon="42.28034468"/>
    <vertex lat="12.46642284" lon="42.37847822"/>
    <vertex lat="12.49437979" lon="42.40860558"/>
    <vertex lat="12.52135489" lon="42.44994673"/>
    <vertex lat="12.51360342" lon="42.4794023"/>
    <vertex lat="12.37658336" lon="42.67008833"/>
    <vertex lat="12.3803299" lon="42.70367801"/>
    <vertex lat="12.42285961" lon="42.76744673"/>
    <vertex lat="12.56936229" lon="42.82532433"/>
    <vertex lat="12.62279572" lon="42.86589033"/>
    <vertex lat="12.62127127" lon="42.88330529"/>
    <vertex lat="12.66232819" lon="43.00567508"/>
    <vertex lat="12.70860444" lon="43.11672774"/>
    <vertex lat="12.66046784" lon="43.1308354"/>
    <vertex lat="12.46389069" lon="43.2985771"/>
    <vertex lat="12.36704906" lon="43.35345747"/>
    <vertex lat="12.18995393" lon="43.40978478"/>
    <vertex lat="12.09125194" lon="43.38032922"/>
    <vertex lat="12.02701813" lon="43.33671431"/>
    <vertex lat="11.96955394" lon="43.27201542"/>
    <vertex lat="11.82904572" lon="43.04804976"/>
    <vertex lat="11.73938711" lon="42.79907271"/>
    <vertex lat="11.56012157" lon="42.64001265"/>
    <vertex lat="11.57216218" lon="42.52177697"/>
    <vertex lat="11.50431102" lon="42.53976037"/>
    <vertex lat="11.49676626" lon="42.58378869"/>
    <vertex lat="11.50955618" lon="42.65272505"/>
    <vertex lat="11.56172354" lon="42.78977095"/>
    <vertex lat="11.58663158" lon="42.91152062"/>
    <vertex lat="11.58849193" lon="43.04277876"/>
    <vertex lat="11.56601268" lon="43.16173791"/>
    <vertex lat="11.49981517" lon="43.24597049"/>
  </area>
</country>
